LICENSE.txt
MANIFEST.in
setup.py
django_redis_sessions.egg-info/PKG-INFO
django_redis_sessions.egg-info/SOURCES.txt
django_redis_sessions.egg-info/dependency_links.txt
django_redis_sessions.egg-info/not-zip-safe
django_redis_sessions.egg-info/requires.txt
django_redis_sessions.egg-info/top_level.txt
redis_sessions/__init__.py
redis_sessions/session.py
redis_sessions/settings.py